<?xml version="1.0" encoding="utf-8" ?>
<dwsync>
<file name="glyphicons-halflings-regular.eot" server="www.his-germany.de" local="130257951674408556" remote="130276084730000000" />
<file name="glyphicons-halflings-regular.woff" server="www.his-germany.de" local="130257951676127295" remote="130276084730000000" />
<file name="glyphicons-halflings-regular.ttf" server="www.his-germany.de" local="130257951675814797" remote="130276084740000000" />
<file name="glyphicons-halflings-regular.svg" server="www.his-germany.de" local="130257951675346050" remote="130270143420000000" />
<file name="Flat-UI-Icons.eot" server="www.his-germany.de" local="130258817970500000" remote="130276084770000000" />
<file name="Flat-UI-Icons.woff" server="www.his-germany.de" local="130258817972843750" remote="130276084770000000" />
<file name="Flat-UI-Icons.ttf" server="www.his-germany.de" local="130258817972218750" remote="130276084770000000" />
<file name="Flat-UI-Icons.dev.svg" server="www.his-germany.de" local="130258817969562500" remote="130270143380000000" />
<file name="Flat-UI-Icons.svg" server="www.his-germany.de" local="130258817971281250" remote="130270143390000000" />
<file name="icomoon-session.json" server="www.his-germany.de" local="130258817978625000" remote="130270143590000000" />
</dwsync>